pyinspector/__init__.py
pyinspector/__main__.py
pyinspector-1.3.dist-info/METADATA
pyinspector-1.3.dist-info/RECORD
pyinspector-1.3.dist-info/WHEEL
pyinspector-1.3.dist-info/entry_points.txt
pyinspector-1.3.dist-info/top_level.txt
