Metadata-Version: 2.1
Name: pyinspector
Version: 1.3
Summary: A module to easely run quality pipeline for python project
Home-page: https://github.com/omauger/pyinspector
Author: Ophélie Mauger
Author-email: UNKNOWN
License: MIT
Platform: UNKNOWN
Requires-Dist: flake8
Requires-Dist: coverage
Requires-Dist: pylint
Requires-Dist: radon
Requires-Dist: xenon
Requires-Dist: coloredlogs
Requires-Dist: verboselogs
